textglow
