Metadata-Version: 2.1
Name: textglow
Version: 0.1.1
Summary: A Python package to add glow effects to text in terminal-based applications.
Author: JVR2022
Author-email: joshuavanrijswijk@outlook.com
Classifier: Programming Language :: Python :: 3
Classifier: License :: OSI Approved :: MIT License
Classifier: Operating System :: OS Independent
License-File: LICENSE
